odoo/addons/stock_putaway_hook/README.rst
odoo/addons/stock_putaway_hook/__init__.py
odoo/addons/stock_putaway_hook/__manifest__.py
odoo/addons/stock_putaway_hook/i18n/stock_putaway_hook.pot
odoo/addons/stock_putaway_hook/models/__init__.py
odoo/addons/stock_putaway_hook/models/stock_location.py
odoo/addons/stock_putaway_hook/models/stock_putaway_rule.py
odoo/addons/stock_putaway_hook/readme/CONTRIBUTORS.rst
odoo/addons/stock_putaway_hook/readme/DESCRIPTION.rst
odoo/addons/stock_putaway_hook/readme/USAGE.rst
odoo/addons/stock_putaway_hook/static/description/icon.png
odoo/addons/stock_putaway_hook/static/description/index.html
odoo13_addon_stock_putaway_hook-13.0.1.1.0.dist-info/METADATA
odoo13_addon_stock_putaway_hook-13.0.1.1.0.dist-info/WHEEL
odoo13_addon_stock_putaway_hook-13.0.1.1.0.dist-info/top_level.txt
odoo13_addon_stock_putaway_hook-13.0.1.1.0.dist-info/RECORD
